setup.py
ycl/__init__.py
ycl.egg-info/PKG-INFO
ycl.egg-info/SOURCES.txt
ycl.egg-info/dependency_links.txt
ycl.egg-info/top_level.txt