Metadata-Version: 1.1
Name: ycl
Version: 0.1
Summary: YAML config loader
Home-page: https://github.com/prymitive/yaml_config_loader
Author: Łukasz Mierzwa
Author-email: l.mierzwa@gmail.com
License: GPLv3
Platform: any
Classifier: License :: OSI Approved :: GNU General Public License v3 (GPLv3)
Classifier: Intended Audience :: Developers
Classifier: Programming Language :: Python
Classifier: Topic :: Software Development :: Libraries :: Python Modules
